{
  "objectInfo" : {
    "id" : "9aIjkJIfmzkd9jE9u5bKcy",
    "name" : "VCS_OtherLanguages_CMD_सह_ねがいします_çãâàá",
    "type" : "DTEMPLATE",
    "metadata" : {
      "modelVersion" : {
        "major" : 0,
        "minor" : 0
      },
      "repoInfo" : {
        "repoHandle" : "010FX317000000000002"
      },
      "contextAttributes" : [ {
        "name" : "id",
        "value" : "@1"
      } ],
      "additionalInfo" : {
        "description" : "Pod Certification Task: Mapping has a src and a target. ",
        "contentType" : "JSON",
        "documentState" : "VALID"
      }
    }
  },
  "dataFileExtension" : "zip",
  "updateTime" : "2023-11-06T15:02:30.646Z",
  "objectRefs" : [ {
    "id" : "aWq4gpGRMRRgX5cSc1Vr4Q",
    "name" : "SQL_Server_PodCertification",
    "type" : "Connection",
    "metadata" : {
      "modelVersion" : {
        "major" : 0,
        "minor" : 0
      },
      "repoInfo" : {
        "repoHandle" : "010FX30B000000000002"
      },
      "contextAttributes" : null,
      "additionalInfo" : {
        "description" : "SQL Server connection for Pod Certification Automation",
        "contentType" : "JSON",
        "documentState" : "COMPLETE"
      }
    },
    "path" : "/SYS"
  }, {
    "id" : "bwzBR46EqOhfzK0NNGoIGI",
    "name" : "FF_PodCertification",
    "type" : "Connection",
    "metadata" : {
      "modelVersion" : {
        "major" : 0,
        "minor" : 0
      },
      "repoInfo" : {
        "repoHandle" : "010FX30B000000000003"
      },
      "contextAttributes" : null,
      "additionalInfo" : {
        "description" : "Flat File connection for Pod Certification Automation",
        "contentType" : "JSON",
        "documentState" : "COMPLETE"
      }
    },
    "path" : "/SYS"
  } ]
}