{
  "objectInfo" : {
    "id" : "6imXCypR0UHkzO9sJms6Sh",
    "name" : "VCS_OtherLanguages_folder_सह_ねがいします_çãâàá",
    "type" : "Folder",
    "metadata" : {
      "modelVersion" : {
        "major" : 0,
        "minor" : 0
      },
      "repoInfo" : null,
      "contextAttributes" : [ ],
      "additionalInfo" : {
        "description" : "",
        "contentType" : "Binary",
        "documentState" : "COMPLETE"
      }
    }
  },
  "dataFileExtension" : "json",
  "updateTime" : "2023-09-04T10:37:58.733Z",
  "objectRefs" : [ ]
}