{
  "objectInfo" : {
    "id" : "aKc8OEbzn0liBmfjhtdoyb",
    "name" : "VCS_OtherLanguages_CMD_सह_ねがいします_çãâàá",
    "type" : "DTEMPLATE",
    "metadata" : {
      "modelVersion" : {
        "major" : 0,
        "minor" : 0
      },
      "repoInfo" : {
        "repoHandle" : "010DNT17000000000002"
      },
      "contextAttributes" : [ {
        "name" : "id",
        "value" : "@1"
      } ],
      "additionalInfo" : {
        "description" : "Pod Certification Task: Mapping has a src and a target. ",
        "contentType" : "JSON",
        "documentState" : "VALID"
      }
    }
  },
  "dataFileExtension" : "zip",
  "updateTime" : "2024-05-11T04:51:00.789Z",
  "objectRefs" : [ {
    "id" : "dFCig0tCFURiwpW96StwmJ",
    "name" : "FF_PodCertification",
    "type" : "Connection",
    "metadata" : {
      "modelVersion" : {
        "major" : 0,
        "minor" : 0
      },
      "repoInfo" : {
        "repoHandle" : "010DNT0B000000000003"
      },
      "contextAttributes" : null,
      "additionalInfo" : {
        "description" : "Flat File connection for Pod Certification Automation",
        "contentType" : "JSON",
        "documentState" : "COMPLETE"
      }
    },
    "path" : "/SYS"
  }, {
    "id" : "4HO8vFPJV2occBsRuJmRsl",
    "name" : "SQL_Server_PodCertification",
    "type" : "Connection",
    "metadata" : {
      "modelVersion" : {
        "major" : 0,
        "minor" : 0
      },
      "repoInfo" : {
        "repoHandle" : "010DNT0B000000000002"
      },
      "contextAttributes" : null,
      "additionalInfo" : {
        "description" : "SQL Server connection for Pod Certification Automation",
        "contentType" : "JSON",
        "documentState" : "COMPLETE"
      }
    },
    "path" : "/SYS"
  } ]
}