{
  "objectInfo" : {
    "id" : "3DrVwjUGEA5lfpsqOXEaqz",
    "name" : "VCS_ForceUndoCheckoutTest",
    "type" : "Project",
    "metadata" : {
      "modelVersion" : {
        "major" : 0,
        "minor" : 0
      },
      "repoInfo" : null,
      "contextAttributes" : [ ],
      "additionalInfo" : {
        "description" : "",
        "contentType" : "Binary",
        "documentState" : "COMPLETE"
      }
    }
  },
  "dataFileExtension" : "json",
  "updateTime" : "2023-10-31T08:14:15.645Z",
  "objectRefs" : [ ]
}