{
  "objectInfo" : {
    "id" : "5lTTboPLU0rico9OosQCOI",
    "name" : "VCSCommitHistoryFolder",
    "type" : "Folder",
    "metadata" : {
      "modelVersion" : {
        "major" : 0,
        "minor" : 0
      },
      "repoInfo" : null,
      "contextAttributes" : [ ],
      "additionalInfo" : {
        "description" : "",
        "contentType" : null,
        "documentState" : "COMPLETE"
      }
    }
  },
  "dataFileExtension" : "json",
  "updateTime" : "2023-11-06T15:58:16.325Z",
  "objectRefs" : [ ]
}