{
  "objectInfo" : {
    "id" : "49m2306woryfn0PWshlfSC",
    "name" : "MultiProjPullDependency1_renameYzU3MWM3MWMtYTlhYi00ZW",
    "type" : "Project",
    "metadata" : {
      "modelVersion" : {
        "major" : 0,
        "minor" : 0
      },
      "repoInfo" : null,
      "contextAttributes" : [ ],
      "additionalInfo" : {
        "description" : "created with automation",
        "contentType" : "Binary",
        "documentState" : "COMPLETE"
      }
    }
  },
  "dataFileExtension" : "json",
  "objectRefs" : [ ]
}