{
  "objectInfo" : {
    "id" : "7Cai9UDMqojk5NCACg510O",
    "name" : "VCS_OtherLanguages_Estáसह_ねがいします_çãâàá",
    "type" : "Project",
    "metadata" : {
      "modelVersion" : {
        "major" : 0,
        "minor" : 0
      },
      "repoInfo" : null,
      "contextAttributes" : [ ],
      "additionalInfo" : {
        "description" : "",
        "contentType" : "Binary",
        "documentState" : "COMPLETE"
      }
    }
  },
  "dataFileExtension" : "json",
  "updateTime" : "2023-08-31T13:23:09.836Z",
  "objectRefs" : [ ]
}