{
  "objectInfo" : {
    "id" : "d0FCizu4YQKiEcCOm7rbMW",
    "name" : "VCSBranchTest_CMD",
    "type" : "DTEMPLATE",
    "metadata" : {
      "modelVersion" : {
        "major" : 0,
        "minor" : 0
      },
      "repoInfo" : {
        "repoHandle" : "010LMC17000000000002"
      },
      "contextAttributes" : [ {
        "name" : "id",
        "value" : "@1"
      } ],
      "additionalInfo" : {
        "description" : "Multiple Lookup Condition",
        "contentType" : "JSON",
        "documentState" : "VALID"
      }
    }
  },
  "dataFileExtension" : "zip",
  "updateTime" : "2024-04-05T19:12:42.551Z",
  "objectRefs" : [ {
    "id" : "80NbZ4wnd4FbSbUk0C65k4",
    "name" : "FF",
    "type" : "Connection",
    "metadata" : {
      "modelVersion" : {
        "major" : 0,
        "minor" : 0
      },
      "repoInfo" : {
        "repoHandle" : "010LMC0B000000000002"
      },
      "contextAttributes" : null,
      "additionalInfo" : {
        "description" : "test desc",
        "contentType" : "JSON",
        "documentState" : "COMPLETE"
      }
    },
    "path" : "/SYS"
  } ]
}