{
  "objectInfo" : {
    "id" : "64LYpGJUqeOj9WUyOpHA2Y",
    "name" : "VCS_MultiRecUnlink",
    "type" : "Project",
    "metadata" : {
      "modelVersion" : {
        "major" : 0,
        "minor" : 0
      },
      "repoInfo" : null,
      "contextAttributes" : [ ],
      "additionalInfo" : {
        "description" : "",
        "contentType" : "Binary",
        "documentState" : "COMPLETE"
      }
    }
  },
  "dataFileExtension" : "json",
  "updateTime" : "2024-01-28T14:56:23.258Z",
  "objectRefs" : [ ]
}