{
  "objectInfo" : {
    "id" : "eoxp7eXO1yVbhp3ybtncqu",
    "name" : "BulkUnlinkTestProj1",
    "type" : "Project",
    "metadata" : {
      "modelVersion" : {
        "major" : 0,
        "minor" : 0
      },
      "repoInfo" : null,
      "contextAttributes" : [ ],
      "additionalInfo" : {
        "description" : "",
        "contentType" : "Binary",
        "documentState" : "COMPLETE"
      }
    }
  },
  "dataFileExtension" : "json",
  "updateTime" : "2024-04-20T07:39:55.979Z",
  "objectRefs" : [ ]
}