{
  "objectInfo" : {
    "id" : "hZeElui8fSSf5X44jlXV8g",
    "name" : "VCS_Asset_Mapping_SQL_FF_1",
    "type" : "DTEMPLATE",
    "metadata" : {
      "modelVersion" : {
        "major" : 0,
        "minor" : 0
      },
      "repoInfo" : {
        "repoHandle" : "0104Y717000000000004"
      },
      "contextAttributes" : [ {
        "name" : "id",
        "value" : "@1"
      } ],
      "additionalInfo" : {
        "description" : "Pod Certification Task: Mapping has a src and a target. ",
        "contentType" : "JSON",
        "documentState" : "VALID"
      }
    }
  },
  "dataFileExtension" : "zip",
  "updateTime" : "2023-09-08T23:27:42.726Z",
  "objectRefs" : [ {
    "id" : "3e9aAMg2JwSiPtJO6K7sSD",
    "name" : "FF_PodCertification",
    "type" : "Connection",
    "metadata" : {
      "modelVersion" : {
        "major" : 0,
        "minor" : 0
      },
      "repoInfo" : {
        "repoHandle" : "0104Y70B000000000003"
      },
      "contextAttributes" : null,
      "additionalInfo" : {
        "description" : "Flat File connection for Pod Certification Automation",
        "contentType" : "JSON",
        "documentState" : "COMPLETE"
      }
    },
    "path" : "/SYS"
  }, {
    "id" : "3dJUSJYla8bkR9DsNukzoj",
    "name" : "SQL_Server_PodCertification",
    "type" : "Connection",
    "metadata" : {
      "modelVersion" : {
        "major" : 0,
        "minor" : 0
      },
      "repoInfo" : {
        "repoHandle" : "0104Y70B000000000002"
      },
      "contextAttributes" : null,
      "additionalInfo" : {
        "description" : "SQL Server connection for Pod Certification Automation",
        "contentType" : "JSON",
        "documentState" : "COMPLETE"
      }
    },
    "path" : "/SYS"
  } ]
}