{
  "objectInfo" : {
    "id" : "ab0FWJxVmgxc52khRea0ah",
    "name" : "cmd_inlineActionDepen",
    "type" : "DTEMPLATE",
    "metadata" : {
      "modelVersion" : {
        "major" : 0,
        "minor" : 0
      },
      "repoInfo" : {
        "repoHandle" : "016S9217000000000002"
      },
      "contextAttributes" : [ {
        "name" : "id",
        "value" : "@1"
      } ],
      "additionalInfo" : {
        "description" : "Multiple Lookup Condition",
        "contentType" : "JSON",
        "documentState" : "VALID"
      }
    }
  },
  "dataFileExtension" : "zip",
  "updateTime" : "2023-09-25T23:43:42.289Z",
  "objectRefs" : [ {
    "id" : "9qvOYimzRx6hQRe0aROm6g",
    "name" : "FF",
    "type" : "Connection",
    "metadata" : {
      "modelVersion" : {
        "major" : 0,
        "minor" : 0
      },
      "repoInfo" : {
        "repoHandle" : "016S920B000000000003"
      },
      "contextAttributes" : null,
      "additionalInfo" : {
        "description" : "test desc",
        "contentType" : "JSON",
        "documentState" : "COMPLETE"
      }
    },
    "path" : "/SYS"
  } ]
}